pyautoflow/__init__.py
pyautoflow/controls.py
pyautoflow/info.py
pyautoflow/inputs.py
pyautoflow/power.py
pyautoflow-1.3.1.dist-info/LICENSE
pyautoflow-1.3.1.dist-info/LICENSE.txt
pyautoflow-1.3.1.dist-info/METADATA
pyautoflow-1.3.1.dist-info/WHEEL
pyautoflow-1.3.1.dist-info/top_level.txt
pyautoflow-1.3.1.dist-info/RECORD
