Metadata-Version: 2.1
Name: pyautoflow
Version: 1.3.1
Summary: A module used to automate a system easily
Author-email: Daniel Drury <daniel-drury@outlook.com>
Project-URL: Homepage, https://github.com/Chickpeaplane/pyautoflow
Project-URL: Bug Tracker, https://github.com/Chickpeaplane/pyautoflow/issues
Classifier: Programming Language :: Python :: 3.10
Classifier: License :: OSI Approved :: GNU General Public License v3 (GPLv3)
Classifier: Operating System :: OS Independent
Requires-Python: >=3.8
License-File: LICENSE
License-File: LICENSE.txt
Requires-Dist: keyboard
Requires-Dist: mouse
Requires-Dist: SimpleSystem
Requires-Dist: numpy
Requires-Dist: opencv-python
Requires-Dist: pyautogui
Requires-Dist: psutil
